<?xml version="1.0"?>
<b:Sources SelectedStyle="" xmlns:b="http://schemas.openxmlformats.org/officeDocument/2006/bibliography" xmlns="http://schemas.openxmlformats.org/officeDocument/2006/bibliography"><b:Source><b:Tag>LiR12</b:Tag><b:SourceType>BookSection</b:SourceType><b:Guid>{86F121A5-E7C2-48DE-AFFA-2ABC8B8BC4DA}</b:Guid><b:Title>TEDAS: A Twitter-based Event Detection and Analysis System</b:Title><b:BookTitle>2012 IEEE 28th International Conference on Data Engineering (ICDE)</b:BookTitle><b:Year>2012</b:Year><b:Pages>1273 - 1276</b:Pages><b:City>Washington, DC</b:City><b:Publisher>IEEE</b:Publisher><b:Author><b:Author><b:NameList><b:Person><b:Last>Li</b:Last><b:First>Rui</b:First></b:Person><b:Person><b:Last>Hou Lei</b:Last><b:First>Kin </b:First></b:Person><b:Person><b:Last>Khadiwala</b:Last><b:First>R</b:First></b:Person><b:Person><b:Last>Chang</b:Last><b:First>K.C.-C.</b:First></b:Person></b:NameList></b:Author></b:Author><b:YearAccessed>2015</b:YearAccessed><b:MonthAccessed>Maart</b:MonthAccessed><b:DayAccessed>9</b:DayAccessed><b:RefOrder>2</b:RefOrder></b:Source><b:Source><b:Tag>Abe12</b:Tag><b:SourceType>BookSection</b:SourceType><b:Guid>{3BD476A8-896F-4159-869A-D79093E3E15E}</b:Guid><b:Title>Twitcident: Fighting Fire with Information from Social Web Streams</b:Title><b:Year>2012</b:Year><b:City>Lyon, France</b:City><b:Publisher>Companion Volume</b:Publisher><b:Author><b:Author><b:NameList><b:Person><b:Last>Abel</b:Last><b:First>Fabian</b:First></b:Person><b:Person><b:Last>Hauff</b:Last><b:First>Claudia</b:First></b:Person><b:Person><b:Last>Houben</b:Last><b:First>Geert-Jan</b:First></b:Person><b:Person><b:Last>Tao</b:Last><b:First>Ke</b:First></b:Person><b:Person><b:Last>Stronkman</b:Last><b:First>Richard</b:First></b:Person></b:NameList></b:Author></b:Author><b:Pages>305-308</b:Pages><b:BookTitle>WWW 2012, Proceedings of the 21st World Wide Web Conference 2012</b:BookTitle><b:DayAccessed>9</b:DayAccessed><b:RefOrder>1</b:RefOrder><b:YearAccessed>2015</b:YearAccessed><b:MonthAccessed>Maart</b:MonthAccessed></b:Source><b:Source><b:Tag>Bea05</b:Tag><b:SourceType>Patent</b:SourceType><b:Guid>{2438E3F5-FB83-4C33-9646-5A87D4E35EA7}</b:Guid><b:Title>Compact text encoding of latitude/longitude coordinates</b:Title><b:Year>2005</b:Year><b:Author><b:Inventor><b:NameList><b:Person><b:Last>Beatty</b:Last><b:First>Bryan</b:First><b:Middle>Kendall (Sammamish, WA, US)</b:Middle></b:Person></b:NameList></b:Inventor></b:Author><b:CountryRegion>United States</b:CountryRegion><b:PatentNumber>20050023524</b:PatentNumber><b:YearAccessed>2015</b:YearAccessed><b:MonthAccessed>April</b:MonthAccessed><b:DayAccessed>15</b:DayAccessed></b:Source><b:Source><b:Tag>Man08</b:Tag><b:SourceType>BookSection</b:SourceType><b:Guid>{D4E2B8B8-B6AC-4B68-8C23-3DE074DFBE64}</b:Guid><b:Author><b:Author><b:NameList><b:Person><b:Last>Manning</b:Last><b:First>Chrisopher</b:First><b:Middle>D.</b:Middle></b:Person><b:Person><b:Last>Raghavan</b:Last><b:First>Prabhakar</b:First></b:Person><b:Person><b:Last>Schütze</b:Last><b:First>Hinrich</b:First></b:Person></b:NameList></b:Author><b:BookAuthor><b:NameList><b:Person><b:Last>Manning</b:Last><b:First>Chrisopher</b:First><b:Middle>D.</b:Middle></b:Person><b:Person><b:Last>Raghavan</b:Last><b:First>Prabhakar</b:First></b:Person><b:Person><b:Last>Schütze</b:Last><b:First>Hinrich</b:First></b:Person></b:NameList></b:BookAuthor></b:Author><b:Title>13 Text Classification and Naive Bayes</b:Title><b:Year>2008</b:Year><b:Pages>206,207, 234-242</b:Pages><b:BookTitle>Introduction to Information Retrieval</b:BookTitle><b:City>Cambridge</b:City><b:Publisher>Cambridge University Press</b:Publisher><b:RefOrder>3</b:RefOrder></b:Source><b:Source><b:Tag>Kak11</b:Tag><b:SourceType>DocumentFromInternetSite</b:SourceType><b:Guid>{134143AA-F14D-41AB-A1DA-72B9199E23FB}</b:Guid><b:Title>Domain Adaptation: Overfitting and Small Sample Statistics</b:Title><b:Year>2011</b:Year><b:Author><b:Author><b:NameList><b:Person><b:Last>Kakade</b:Last><b:First>Sham</b:First></b:Person><b:Person><b:Last>Foster</b:Last><b:First>Dean</b:First></b:Person><b:Person><b:Last>Salakhutdinov</b:Last><b:First>Ruslan</b:First></b:Person></b:NameList></b:Author></b:Author><b:YearAccessed>2015</b:YearAccessed><b:MonthAccessed>Mei</b:MonthAccessed><b:DayAccessed>16</b:DayAccessed><b:URL>http://arxiv.org/abs/1105.0857v1</b:URL><b:InternetSiteTitle>Cornell University Library</b:InternetSiteTitle></b:Source></b:Sources>
